restmapi/__init__.py
restmapi/services.py
restmapi/version.txt
restmapi-1.0.5.0.dist-info/LICENSE
restmapi-1.0.5.0.dist-info/METADATA
restmapi-1.0.5.0.dist-info/WHEEL
restmapi-1.0.5.0.dist-info/top_level.txt
restmapi-1.0.5.0.dist-info/RECORD
