Metadata-Version: 2.1
Name: restmapi
Version: 1.0.5.0
Summary: MORPHEE REST API SDK
Home-page: https://dev.azure.com/STS-Software/MORPHEE/_git/TOOLS-REST-MAPI?path=/Python
Author: Xavier Dourille
Author-email: xavier.dourille@enorise.com
Classifier: Programming Language :: Python :: 3
Classifier: License :: OSI Approved :: MIT License
License-File: LICENSE
Requires-Dist: requests>=2.25
Requires-Dist: psutil>=5.9.8
Requires-Dist: signalr-client>=0.0.7
